{
  "kirish": "Kirish",
  "-- b": {
    "type": "separator",
    "title": "🟢 Boshlang'ich"
  },
  "shifrlash-asoslari": "Shifrlash asoslari: sirni qanday yashirish",
  "hash": "Hash funksiyalar: parolni qaytarib boʻlmas qilish",
  "simmetrik-asimmetrik": "Simmetrik vs asimmetrik: bitta kalitmi yoki ikkita?",
  "-- i": {
    "type": "separator",
    "title": "🟡 O'rtacha"
  },
  "tls-https": "TLS/HTTPS: internetdagi ishonch qanday quriladi",
  "pki": "PKI va sertifikatlar: raqamli pasportlar",
  "-- a": {
    "type": "separator",
    "title": "🔴 Murakkab"
  },
  "kripto-hujumlar": "Kriptografik hujumlar: matematikani sindirish",
  "post-kvant": "Post-kvant kriptografiya: kelajak tahdidiga tayyorgarlik"
}
